cavaMy/MongoDB.py
cavaMy/SqliteManage.py
cavaMy/__init__.py
cavaMy/__version__.py
DBLaobor-0.0.10.dist-info/LICENSE
DBLaobor-0.0.10.dist-info/METADATA
DBLaobor-0.0.10.dist-info/WHEEL
DBLaobor-0.0.10.dist-info/top_level.txt
DBLaobor-0.0.10.dist-info/RECORD
