Metadata-Version: 2.1
Name: DBLaobor
Version: 0.0.10
Summary: The way About DB Operation
Home-page: https://github.com/augwewe/DBLaobor
Author: cava
Author-email: 1085816416@qq.com
License: MIT
Classifier: License :: OSI Approved :: MIT License
Classifier: Programming Language :: Python
Classifier: Programming Language :: Python :: 3
Classifier: Programming Language :: Python :: 3.6
Classifier: Programming Language :: Python :: Implementation :: CPython
Classifier: Programming Language :: Python :: Implementation :: PyPy
Requires-Python: >=3.6.0
License-File: LICENSE
Requires-Dist: pymongo
Requires-Dist: sqlalchemy
